skink/__init__.py
skink/remote.py
skink/server.py
skink/static/index.html
skink/static/skink.js
skink/static/style.css
Skink-0.3.dist-info/DESCRIPTION.rst
Skink-0.3.dist-info/METADATA
Skink-0.3.dist-info/pydist.json
Skink-0.3.dist-info/RECORD
Skink-0.3.dist-info/top_level.txt
Skink-0.3.dist-info/WHEEL
