Metadata-Version: 2.0
Name: Skink
Version: 0.3
Summary: Control the DOM from Python using Websockets
Home-page: https://github.com/oksome/Skink/
Author: OKso.me
Author-email: @okso.me
License: AGPLv3
Keywords: websockets javascript injection dom
Platform: UNKNOWN
Classifier: Development Status :: 3 - Alpha
Classifier: Environment :: Web Environment
Classifier: Programming Language :: Python :: 3
Classifier: Operating System :: POSIX
Classifier: Operating System :: MacOS :: MacOS X
Classifier: Intended Audience :: End Users/Desktop
Classifier: Intended Audience :: Information Technology
Classifier: License :: OSI Approved :: GNU Affero General Public License v3
Classifier: Topic :: Home Automation
Classifier: Topic :: Scientific/Engineering :: Human Machine Interfaces
Classifier: Topic :: Scientific/Engineering :: Visualization
Requires-Dist: tornado
